LICENSE
MANIFEST.in
README.rst
setup.py
horizon_openfoam/__init__.py
horizon_openfoam/dashboard.py
horizon_openfoam/models.py
horizon_openfoam.egg-info/PKG-INFO
horizon_openfoam.egg-info/SOURCES.txt
horizon_openfoam.egg-info/dependency_links.txt
horizon_openfoam.egg-info/requires.txt
horizon_openfoam.egg-info/top_level.txt
horizon_openfoam/instances/__init__.py
horizon_openfoam/instances/panel.py
horizon_openfoam/instances/tables.py
horizon_openfoam/instances/tabs.py
horizon_openfoam/instances/urls.py
horizon_openfoam/instances/utils.py
horizon_openfoam/instances/views.py
horizon_openfoam/instances/templates/instances/_detail_configurations.html
horizon_openfoam/instances/templates/instances/_detail_log.html
horizon_openfoam/instances/templates/instances/_detail_overview.html
horizon_openfoam/instances/templates/instances/detail.html
horizon_openfoam/instances/templates/instances/index.html
horizon_openfoam/simulations/__init__.py
horizon_openfoam/simulations/panel.py
horizon_openfoam/simulations/tables.py
horizon_openfoam/simulations/tests.py
horizon_openfoam/simulations/urls.py
horizon_openfoam/simulations/utils.py
horizon_openfoam/simulations/views.py
horizon_openfoam/simulations/workflows.py
horizon_openfoam/simulations/templates/simulations/index.html
horizon_openfoam/simulations/templates/simulations/instances.html
horizon_openfoam/static/ofcloud/js/ofcloud.js
horizon_openfoam/static/ofcloud/scss/ofcloud.scss
horizon_openfoam/templates/ofcloud/base.html