Metadata-Version: 1.1
Name: horizon-openfoam
Version: 1.0
Summary: OpenFOAM horizon dashboard app.
Home-page: https://www.xlab.si/
Author: XLAB d.o.o.
Author-email: pypi@xlab.si
License: Apache Software License
Platform: UNKNOWN
Classifier: Environment :: Web Environment
Classifier: Framework :: Django
Classifier: Framework :: Django :: 1.8
Classifier: Intended Audience :: Developers
Classifier: License :: OSI Approved :: Apache Software License
Classifier: Operating System :: OS Independent
Classifier: Programming Language :: Python
Classifier: Programming Language :: Python :: 2.7
Classifier: Topic :: Internet :: WWW/HTTP
Classifier: Topic :: Internet :: WWW/HTTP :: Dynamic Content
